maleo_token/__init__.py
maleo_token/enums.py
maleo_token/client/__init__.py
maleo_token/client/manager.py
maleo_token/client/services.py
maleo_token/client/controllers/__init__.py
maleo_token/client/controllers/http.py
maleo_token/models/__init__.py
maleo_token/models/schemas.py
maleo_token/models/transfers/__init__.py
maleo_token/models/transfers/general.py
maleo_token/models/transfers/parameters.py
maleo_token/models/transfers/results.py
maleo_token/types/__init__.py
maleo_token/types/results.py
maleo_token-0.0.5.dist-info/METADATA
maleo_token-0.0.5.dist-info/WHEEL
maleo_token-0.0.5.dist-info/top_level.txt
maleo_token-0.0.5.dist-info/RECORD
